{
  "group": "admin",
  "name": "admin.usergroups.removeChannels",
  "deprecated": false,
  "desc": "Remove one or more default channels from an org-level IDP group (user group).",
  "args": {
    "channel_ids": {
      "required": true,
      "example": "C00000000,C00000001",
      "desc": "Comma-separated string of channel IDs.",
      "type": "array"
    },
    "usergroup_id": {
      "required": true,
      "example": "S00000000",
      "desc": "ID of the IDP Group.",
      "type": "string"
    }
  },
  "response": {
    "examples": [
      "{\n    \"ok\": true\n}",
      "{\n    \"ok\": false,\n    \"error\": \"not_an_admin\"\n}"
    ]
  },
  "errors": {
    "channel_not_found": "At least one of the provided channel IDs could not be found, or one of those channels has a type that is not supported.",
    "feature_not_enabled": "The Admin APIs feature is not enabled for this workspace.",
    "invalid_auth": "The workspace specified is not part of this Enterprise organization.",
    "invalid_channels_limit": "The number of channel IDs passed in is larger than 100.",
    "not_an_admin": "The token provided is not associated with an Org Admin or Owner.",
    "not_an_enterprise": "The token passed in does not belong to an Enterprise organization.",
    "usergroup_not_found": "The IDP group provided was not found.",
    "internal_error": "There was an internal error processing this request—please retry."
  }
}