{
  "group": "admin",
  "name": "admin.audit.anomaly.allow.updateItem",
  "deprecated": false,
  "desc": "API to allow Enterprise org admins to write/overwrite the allow list of IP blocks and ASNs from the enterprise configuration.",
  "args": {
    "trusted_asns": {
      "required": false,
      "desc": "allow list of Autonomous System Numbers (ASN) in the Enterprise organization configuration.",
      "type": "array"
    },
    "trusted_cidr": {
      "required": false,
      "desc": "allow list of IPv4 addresses using cidr notation in the Enterprise organization configuration.",
      "type": "array"
    }
  },
  "response": {
    "examples": []
  },
  "errors": {
    "endpoint_unavailable": "The requested endpoint is currently unavailable.",
    "invalid_field_or_data": "user attempted to write and invalid field or data to the team config",
    "unable_to_process_post_request": "The user sent a malformed post request",
    "unsupported_action_describe": "The user specified describe action is unsupported",
    "unsupported_action_put": "The user specified put action is unsupported"
  }
}