{
  "group": "canvases",
  "name": "canvases.access.delete",
  "deprecated": false,
  "desc": "Remove access to a canvas for specified entities",
  "args": {
    "canvas_id": {
      "required": true,
      "example": "F1234ABCD",
      "desc": "Encoded ID of the canvas."
    },
    "channel_ids": {
      "required": false,
      "example": "[\"C1234ABCD\"]",
      "desc": "List of channels you wish to update access for.",
      "type": "array"
    },
    "user_ids": {
      "required": false,
      "example": "[\"U1234ABCD\"]",
      "desc": "List of users you wish to update access for.",
      "type": "array"
    }
  },
  "response": {
    "examples": [
      "{\n    \"ok\": true\n}",
      "{\n    \"ok\": false,\n    \"error\": \"canvas_not_found\"\n}"
    ]
  },
  "errors": {
    "canvas_not_found": "The canvas you wish to revoke permissions for is not available.",
    "restricted_action": "User does not have permission to perform this action.",
    "canvas_disabled_user_team": "Canvas is disabled on user's team.",
    "invalid_parameters": "One of user_ids and channel_ids must be defined.",
    "channel_not_found": "A channel could not be found.",
    "user_not_found": "A user could not be found."
  }
}